{
    "MAIN": {
        "1": {
            "alternatives": null,
            "contact_info": null,
            "created_at": 1628883441.117576,
            "description": "Qiskit is an open-source SDK for working with quantum computers at the level of circuits, algorithms, and application modules. Qiskit is made up of elements that work together to enable quantum computing. This is a simple meta-package to install the elements of Qiskit altogether.",
            "labels": [
                "meta"
            ],
            "licence": "Apache 2.0",
            "name": "qiskit",
            "tier": "MAIN",
            "updated_at": 1628883441.117589,
            "url": "https://github.com/Qiskit/qiskit",
            "tests_results": []
        },
        "2": {
            "alternatives": null,
            "contact_info": null,
            "created_at": 1628883441.118058,
            "description": "Terra is the foundation on which the rest of Qiskit is built.",
            "labels": [
                "circuit",
                "pulse"
            ],
            "licence": "Apache 2.0",
            "name": "qiskit-terra",
            "tier": "MAIN",
            "updated_at": 1628883441.118061,
            "url": "https://github.com/Qiskit/qiskit-terra",
            "tests_results": []
        },
        "3": {
            "alternatives": null,
            "contact_info": null,
            "created_at": 1636403010.377695,
            "description": "Aer provides high-performance quantum computing simulators with realistic noise models.",
            "labels": [
                "simulation"
            ],
            "licence": "Apache 2.0",
            "name": "qiskit-aer",
            "tier": "MAIN",
            "updated_at": 1636403010.377697,
            "url": "https://github.com/Qiskit/qiskit-aer",
            "tests_results": [
                {
                    "test_type": "STANDARD",
                    "passed": true,
                    "terra_version": "0.18.3",
                    "timestamp": 1636403010.377469
                }
            ],
            "affiliations": null,
            "styles_results": [],
            "coverages_results": []
        },
        "4": {
            "alternatives": null,
            "contact_info": null,
            "created_at": 1636403009.538761,
            "description": "Qiskit Optimization is an open-source framework that covers the whole range from high-level modeling of optimization problems, with automatic conversion of problems to different required representations, to a suite of easy-to-use quantum optimization algorithms that are ready to run on classical simulators, as well as on real quantum devices via Qiskit.",
            "labels": [
                "algorithms",
                "optimization"
            ],
            "licence": "Apache 2.0",
            "name": "qiskit-optimization",
            "tier": "MAIN",
            "updated_at": 1636403009.538763,
            "url": "https://github.com/Qiskit/qiskit-optimization",
            "tests_results": [
                {
                    "test_type": "DEV_COMPATIBLE",
                    "passed": true,
                    "terra_version": "0.19.0",
                    "timestamp": 1636403009.53853
                }
            ],
            "affiliations": null,
            "styles_results": [],
            "coverages_results": []
        },
        "5": {
            "alternatives": null,
            "contact_info": null,
            "created_at": 1628883441.119202,
            "description": "Qiskit Metal is an open-source framework for engineers and scientists to design superconducting quantum devices with ease.",
            "labels": [
                "hardware",
                "design"
            ],
            "licence": "Apache 2.0",
            "name": "qiskit-metal",
            "tier": "MAIN",
            "updated_at": 1628883441.119205,
            "url": "https://github.com/Qiskit/qiskit-metal",
            "tests_results": []
        },
        "6": {
            "alternatives": null,
            "contact_info": null,
            "created_at": 1636403010.012954,
            "description": "The Machine Learning package contains sample datasets and quantum ML algorithms.",
            "labels": [
                "algorithms",
                "ml"
            ],
            "licence": "Apache 2.0",
            "name": "qiskit-machine-learning",
            "tier": "MAIN",
            "updated_at": 1636403010.012956,
            "url": "https://github.com/Qiskit/qiskit-machine-learning",
            "tests_results": [
                {
                    "test_type": "DEV_COMPATIBLE",
                    "passed": true,
                    "terra_version": "0.19.0",
                    "timestamp": 1636403010.012718
                }
            ],
            "affiliations": null,
            "styles_results": [],
            "coverages_results": []
        },
        "7": {
            "alternatives": null,
            "contact_info": null,
            "created_at": 1636403009.16708,
            "description": "Qiskit Nature allows researchers and developers in different areas of natural sciences (including physics, chemistry, material science and biology) to model and solve domain-specific problems using quantum simulations",
            "labels": [
                "algorithms",
                "physics",
                "chemistry"
            ],
            "licence": "Apache 2.0",
            "name": "qiskit-nature",
            "tier": "MAIN",
            "updated_at": 1636403009.167082,
            "url": "https://github.com/Qiskit/qiskit-nature",
            "tests_results": [
                {
                    "test_type": "DEV_COMPATIBLE",
                    "passed": true,
                    "terra_version": "0.19.0",
                    "timestamp": 1636403009.166847
                }
            ],
            "affiliations": null,
            "styles_results": [],
            "coverages_results": []
        },
        "8": {
            "alternatives": null,
            "contact_info": null,
            "created_at": 1636403009.368607,
            "description": "Qiskit Finance is an open-source framework that contains uncertainty components for stock/securities problems, Ising translators for portfolio optimizations and data providers to source real or random data to finance experiments.",
            "labels": [
                "algorithms",
                "finance"
            ],
            "licence": "Apache 2.0",
            "name": "qiskit-finance",
            "tier": "MAIN",
            "updated_at": 1636403009.368609,
            "url": "https://github.com/Qiskit/qiskit-finance",
            "tests_results": [
                {
                    "test_type": "DEV_COMPATIBLE",
                    "passed": true,
                    "terra_version": "0.19.0",
                    "timestamp": 1636403009.368369
                }
            ],
            "affiliations": null,
            "styles_results": [],
            "coverages_results": []
        },
        "9": {
            "alternatives": null,
            "contact_info": null,
            "created_at": 1628883441.120706,
            "description": "Collection of Jupyter notebooks aimed at teaching people who want to use Qiskit for writing quantum computing programs, and executing them on one of several backends.",
            "labels": [
                "education",
                "community"
            ],
            "licence": "Apache 2.0",
            "name": "qiskit-tutorials",
            "tier": "MAIN",
            "updated_at": 1628883441.120709,
            "url": "https://github.com/Qiskit/qiskit-tutorials",
            "tests_results": []
        },
        "10": {
            "alternatives": null,
            "contact_info": null,
            "created_at": 1628883441.121108,
            "description": "Qiskit's website",
            "labels": [
                "community",
                "web"
            ],
            "licence": "Apache 2.0",
            "name": "qiskit.org",
            "tier": "MAIN",
            "updated_at": 1628883441.121111,
            "url": "https://github.com/Qiskit/qiskit.org",
            "tests_results": []
        }
    },
    "COMMUNITY": {
        "1": {
            "name": "pyEPR",
            "url": "https://github.com/zlatko-minev/pyEPR",
            "description": "Qiskit Metal E&M analysis with Ansys and the energy-participation-ratio method is based on pyEPR.",
            "licence": "BSD 3-Clause New or Revised license",
            "contact_info": "zlatko.minev@ibm.com",
            "alternatives": "",
            "affiliations": null,
            "labels": [
                "plugin"
            ],
            "created_at": 1637598842.741817,
            "updated_at": 1637598842.74182,
            "tests_results": [
                {
                    "test_type": "STANDARD",
                    "passed": false,
                    "terra_version": "0.18.3",
                    "timestamp": 1637598842.74177
                },
                {
                    "test_type": "STANDARD",
                    "passed": false,
                    "terra_version": "-",
                    "timestamp": 1637598842.741779
                },
                {
                    "test_type": "STABLE_COMPATIBLE",
                    "passed": false,
                    "terra_version": "0.18.3",
                    "timestamp": 1637598842.741782
                },
                {
                    "test_type": "DEV_COMPATIBLE",
                    "passed": false,
                    "terra_version": "0.19.0",
                    "timestamp": 1637598842.741783
                }
            ],
            "styles_results": [
                {
                    "style_type": "pylint",
                    "passed": false
                }
            ],
            "coverages_results": [
                {
                    "coverage_type": "",
                    "passed": false
                }
            ],
            "tier": "COMMUNITY"
        },
        "2": {
            "name": "qiskit-ecosystem_template",
            "url": "https://github.com/mickahell/qiskit-ecosystem_template",
            "description": "Project template for adding to Qiskit Ecosystem",
            "licence": "Apache License 2.0",
            "contact_info": "michael.rollin@protonmail.com",
            "alternatives": "_No response_",
            "affiliations": null,
            "labels": [
                "tool"
            ],
            "created_at": 1638725396.209793,
            "updated_at": 1638725396.209796,
            "tests_results": [
                {
                    "test_type": "STANDARD",
                    "passed": true,
                    "terra_version": "0.18.3",
                    "timestamp": 1638725396.209749
                },
                {
                    "test_type": "STABLE_COMPATIBLE",
                    "passed": true,
                    "terra_version": "0.18.3",
                    "timestamp": 1638725396.209755
                },
                {
                    "test_type": "DEV_COMPATIBLE",
                    "passed": true,
                    "terra_version": "0.19.0",
                    "timestamp": 1638725396.209238
                }
            ],
            "styles_results": [
                {
                    "style_type": "pylint",
                    "passed": true
                }
            ],
            "coverages_results": [
                {
                    "coverage_type": "",
                    "passed": true
                }
            ],
            "tier": "COMMUNITY"
        },
        "3": {
            "name": "c3",
            "url": "https://github.com/q-optimize/c3",
            "description": "The C3 package is intended to close the loop between open-loop control optimization, control pulse calibration, and model-matching based on calibration data.",
            "licence": "Apache-2.0 License",
            "contact_info": "",
            "alternatives": "",
            "affiliations": null,
            "labels": [
                "plugin"
            ],
            "created_at": 1637601916.875402,
            "updated_at": 1637601916.875404,
            "tests_results": [
                {
                    "test_type": "STANDARD",
                    "passed": true,
                    "terra_version": "0.18.3",
                    "timestamp": 1637601916.875342
                },
                {
                    "test_type": "STABLE_COMPATIBLE",
                    "passed": true,
                    "terra_version": "0.18.3",
                    "timestamp": 1637601916.875354
                },
                {
                    "test_type": "DEV_COMPATIBLE",
                    "passed": false,
                    "terra_version": "0.19.0",
                    "timestamp": 1637601916.875356
                }
            ],
            "styles_results": [
                {
                    "style_type": "pylint",
                    "passed": false
                }
            ],
            "coverages_results": [
                {
                    "coverage_type": "",
                    "passed": false
                }
            ],
            "tier": "COMMUNITY"
        },
        "4": {
            "name": "qiskit-superstaq",
            "url": "https://github.com/SupertechLabs/qiskit-superstaq",
            "description": "This package is used to access SuperstaQ via a Web API through Qiskit. Qiskit programmers can take advantage of the applications, pulse level optimizations, and write-once-target-all features of SuperstaQ with this package.",
            "licence": "Apache-2.0 License",
            "contact_info": "",
            "alternatives": "",
            "affiliations": null,
            "labels": [
                "plugin"
            ],
            "created_at": 1637598871.906623,
            "updated_at": 1637598871.906625,
            "tests_results": [
                {
                    "test_type": "STANDARD",
                    "passed": false,
                    "terra_version": "0.18.3",
                    "timestamp": 1637598871.906568
                },
                {
                    "test_type": "STABLE_COMPATIBLE",
                    "passed": false,
                    "terra_version": "0.18.3",
                    "timestamp": 1637598871.906594
                },
                {
                    "test_type": "DEV_COMPATIBLE",
                    "passed": false,
                    "terra_version": "0.19.0",
                    "timestamp": 1637598871.906596
                }
            ],
            "styles_results": [
                {
                    "style_type": "pylint",
                    "passed": false
                }
            ],
            "coverages_results": [
                {
                    "coverage_type": "",
                    "passed": false
                }
            ],
            "tier": "COMMUNITY"
        },
        "5": {
            "name": "qtcodes",
            "url": "https://github.com/yaleqc/qtcodes",
            "description": "Qiskit Topological Codes",
            "licence": "Apache-2.0 License",
            "contact_info": "",
            "alternatives": "",
            "affiliations": null,
            "labels": [
                "plugin"
            ],
            "created_at": 1637598624.203397,
            "updated_at": 1637598624.203399,
            "tests_results": [
                {
                    "test_type": "STANDARD",
                    "passed": false,
                    "terra_version": "-",
                    "timestamp": 1637598624.203356
                },
                {
                    "test_type": "STABLE_COMPATIBLE",
                    "passed": false,
                    "terra_version": "-",
                    "timestamp": 1637598624.203367
                },
                {
                    "test_type": "DEV_COMPATIBLE",
                    "passed": false,
                    "terra_version": "-",
                    "timestamp": 1637598624.203369
                }
            ],
            "styles_results": [
                {
                    "style_type": "pylint",
                    "passed": false
                }
            ],
            "coverages_results": [
                {
                    "coverage_type": "",
                    "passed": false
                }
            ],
            "tier": "COMMUNITY"
        },
        "6": {
            "name": "kaleidoscope",
            "url": "https://github.com/QuSTaR/kaleidoscope",
            "description": "Kaleidoscope",
            "licence": "Apache-2.0 License",
            "contact_info": "",
            "alternatives": "",
            "affiliations": null,
            "labels": [
                "plugin"
            ],
            "created_at": 1637598913.696201,
            "updated_at": 1637598913.696202,
            "tests_results": [
                {
                    "test_type": "STANDARD",
                    "passed": false,
                    "terra_version": "-",
                    "timestamp": 1637598913.696168
                },
                {
                    "test_type": "STABLE_COMPATIBLE",
                    "passed": false,
                    "terra_version": "0.18.3",
                    "timestamp": 1637598913.696176
                },
                {
                    "test_type": "DEV_COMPATIBLE",
                    "passed": false,
                    "terra_version": "0.19.0",
                    "timestamp": 1637598913.696178
                }
            ],
            "styles_results": [
                {
                    "style_type": "pylint",
                    "passed": false
                }
            ],
            "coverages_results": [
                {
                    "coverage_type": "",
                    "passed": false
                }
            ],
            "tier": "COMMUNITY"
        },
        "7": {
            "name": "qiskit-ecosystem_template",
            "url": "https://github.com/mickahell/qiskit-ecosystem_template",
            "description": "My awesome project !",
            "licence": "Apache License 2.0",
            "contact_info": "toto@qiskit.org",
            "alternatives": "_No response_",
            "affiliations": "Me, my and myself",
            "labels": [
                "paper-implementation"
            ],
            "created_at": 1638725396.576341,
            "updated_at": 1638725396.576346,
            "tests_results": [],
            "styles_results": [],
            "coverages_results": [],
            "tier": "COMMUNITY"
        }
    }
}